<step title="Incoming Request" date="2025-11-29T21:51:09.308" instance="c4a671" url="/api/publish?type=zip&amp;async=False" method="POST" type="request" pid="768,1,5" Accept="*/*" Host="quotrading-flask-api.scm.azurewebsites.net" User-Agent="AZURECLI/2.80.0 (MSI)" Accept-Encoding="gzip, deflate" Authorization="Bea..." Cache-Control="no-cache" Content-Type="application/octet-stream" Cookie="ARRAffinity=c4a671a5f8662a541a877e364dbc007723397b4ed45078d3ae1254f25f96e556; ARRAffinitySameSite=c4a671a5f8662a541a877e364dbc007723397b4ed45078d3ae1254f25f96e556" Content-Length="431707" x-ms-client-request-id="75906581-cd6d-11f0-9ed1-50bbb5629ee1" x-ms-artifact-checksum="67379691d5b9f670cf2f918f998437dae2c9227a5f57722f6a9db75b0b73d8b6" X-ARR-LOG-ID="75906581-cd6d-11f0-9ed1-50bbb5629ee1" CLIENT-IP="69.120.241.138:51174" X-SITE-DEPLOYMENT-ID="quotrading-flask-api" WAS-DEFAULT-HOSTNAME="quotrading-flask-api.scm.azurewebsites.net" X-Forwarded-Proto="https" X-AppService-Proto="https" X-Forwarded-TlsVersion="1.3" X-WAWS-Unencoded-URL="/api/publish?type=zip&amp;async=False" X-Client-IP="69.120.241.138" X-Client-Port="51174" >
  <step title="OneDeploy" date="2025-11-29T21:51:09.395" >
    <step title="None repository commit" date="2025-11-29T21:51:09.410" >
      <step title="Commit id: 2c668a72-01dd-4caf-b595-f53815842508" date="2025-11-29T21:51:09.415" Message="N/A" AuthorName="N/A" AuthorEmail="N/A" /><!-- duration: 3ms -->
    </step><!-- duration: 10ms -->
    <step title="Starting PushDeployAsync" date="2025-11-29T21:51:09.423" /><!-- duration: 3ms -->
    <step title="Writing artifact to /tmp/zipdeploy/fbc939c5-4177-4af9-bc10-f4c94e5bae05.zip" date="2025-11-29T21:51:09.445" >
      <step title="Writing multipart request body to /tmp/zipdeploy/fbc939c5-4177-4af9-bc10-f4c94e5bae05.zip" date="2025-11-29T21:51:09.452" /><!-- duration: 10ms -->
    </step><!-- duration: 71ms -->
    <step title="Removing previous build artifact&apos;s manifest file" date="2025-11-29T21:51:09.531" >
      <step title="Attempting to fetch target branch HEAD" date="2025-11-29T21:51:09.561" /><!-- duration: 8ms -->
      <step title="Acquiring Deployment Lock" date="2025-11-29T21:51:09.573" /><!-- duration: 6ms -->
      <step title="Acquired Deployment Lock" date="2025-11-29T21:51:09.612" /><!-- duration: 3ms -->
      <step title="Performing fetch based deployment" date="2025-11-29T21:51:09.622" >
        <step title="Creating temporary deployment" date="2025-11-29T21:51:09.628" /><!-- duration: 42ms -->
        <step title="Releasing Deployment Lock" date="2025-11-29T21:51:10.819" /><!-- duration: 6ms -->
        <step title="Cleaning up temp folders from previous zip deployments and extracting pushed zip file /tmp/zipdeploy/fbc939c5-4177-4af9-bc10-f4c94e5bae05.zip (0.41 MB) to /tmp/zipdeploy/extracted" date="2025-11-29T21:51:10.851" >
          <step title="ChmodRecursive Process exited with total time taken in ms: 46" date="2025-11-29T21:51:10.933" /><!-- duration: 4ms -->
        </step><!-- duration: 91ms -->
        <step title="None repository commit" date="2025-11-29T21:51:10.949" >
          <step title="Commit id: 2c668a72-01dd-4caf-b595-f53815842508" date="2025-11-29T21:51:10.954" Message="OneDeploy" AuthorName="N/A" AuthorEmail="N/A" /><!-- duration: 3ms -->
        </step><!-- duration: 11ms -->
        <step title="Deployment timer started" date="2025-11-29T21:51:12.968" >
          <step title="DeploymentManager.Deploy(id:2c668a72-01dd-4caf-b595-f53815842508)" date="2025-11-29T21:51:12.975" >
            <step title="Collecting changeset information" date="2025-11-29T21:51:12.991" /><!-- duration: 106ms -->
            <step title="Updating submodules" date="2025-11-29T21:51:13.105" /><!-- duration: 1131ms -->
            <step title="Determining deployment builder" date="2025-11-29T21:51:14.451" >
              <step title="Builder is OryxBuilder" date="2025-11-29T21:51:14.462" /><!-- duration: 3ms -->
            </step><!-- duration: 29ms -->
            <step title="PreDeployment: context.CleanOutputPath False" date="2025-11-29T21:51:14.531" >
              <step title="PreDeployment: context.OutputPath /home/site/wwwroot" date="2025-11-29T21:51:14.652" >
                <step title="Building" date="2025-11-29T21:51:14.801" >
                  <step title="Executing external process" date="2025-11-29T21:51:15.179" type="process" path="bash" arguments="-c &quot;oryx build /tmp/zipdeploy/extracted -o /home/site/wwwroot --platform python --platform-version 3.11 -p virtualenv_name=antenv --log-file /tmp/build-debug.log  -i /tmp/8de2f916afbba5d --compress-destination-dir | tee /tmp/oryx-build.log ; exit $PIPESTATUS &quot;" /><!-- duration: 79547ms -->
                  <step title="Using PythonDeploymentLogParser" date="2025-11-29T21:52:35.368" /><!-- duration: 3ms -->
                  <step title="Modified file to trigger a restart of the app container." date="2025-11-29T21:52:37.163" /><!-- duration: 10ms -->
                  <step title="Skip function trigger and logicapp sync because function is not enabled." date="2025-11-29T21:52:37.200" /><!-- duration: 3ms -->
                  <step title="Purge deployment items" date="2025-11-29T21:52:38.519" >
                    <step title="Remove a87503c3-, Success, received at 11/29/2025 06:31:06" date="2025-11-29T21:52:38.587" /><!-- duration: 3ms -->
                  </step><!-- duration: 74ms -->
                </step><!-- duration: 83878ms -->
              </step><!-- duration: 84035ms -->
              <step title="Cleaning up temp files" date="2025-11-29T21:52:38.689" /><!-- duration: 633ms -->
              <step title="Cleaning up temp files" date="2025-11-29T21:52:39.325" /><!-- duration: 517ms -->
              <step title="Reloading status file with latest updates" date="2025-11-29T21:52:39.903" >
                <step title="WebHooksManager.PublishEventAsync: PostDeployment" date="2025-11-29T21:52:39.908" /><!-- duration: 72ms -->
              </step><!-- duration: 105ms -->
              <step title="Cleaning up temporary deployment - fetch deployment was successful" date="2025-11-29T21:52:40.017" /><!-- duration: 2ms -->
            </step><!-- duration: 85601ms -->
          </step><!-- duration: 87183ms -->
          <step title="Outgoing response" date="2025-11-29T21:52:40.184" type="response" statusCode="200" statusText="OK" /><!-- duration: 4ms -->
        </step><!-- duration: 87223ms -->
