<step title="Incoming Request" date="2025-12-27T23:07:45.576" instance="c25286" url="/api/zipdeploy?isAsync=true" method="POST" type="request" pid="768,1,69" Accept="*/*" Host="quotrading-flask-api.scm.azurewebsites.net" User-Agent="AZURECLI/2.80.0 (MSI)" Accept-Encoding="gzip, deflate" Authorization="Bea..." Cache-Control="no-cache" Content-Type="application/octet-stream" Content-Length="71655" x-ms-client-request-id="d2a72e60-e378-11f0-b35c-50bbb5629ee1" x-ms-artifact-checksum="5e73663c7ac240bfaf9b5d171ca9f657d5b47c7df938618cf0ccef7aaad4a763" X-ARR-LOG-ID="d2a72e60-e378-11f0-b35c-50bbb5629ee1" CLIENT-IP="69.120.241.138:64445" X-SITE-DEPLOYMENT-ID="quotrading-flask-api" WAS-DEFAULT-HOSTNAME="quotrading-flask-api.scm.azurewebsites.net" X-Forwarded-Proto="https" X-AppService-Proto="https" X-Forwarded-TlsVersion="1.3" X-WAWS-Unencoded-URL="/api/zipdeploy?isAsync=true" X-Client-IP="69.120.241.138" X-Client-Port="64445" >
  <step title="Cleanup Xml Logs" date="2025-12-27T23:07:45.580" >
    <step title="Cleanup Infos" date="2025-12-27T23:07:45.624" totalFiles="1325" totalCleanup="1165" /><!-- duration: 9ms -->
  </step><!-- duration: 56ms -->
  <step title="ZipPushDeploy" date="2025-12-27T23:07:45.654" >
    <step title="ZipDeploy. Extract zip. Remote build." date="2025-12-27T23:07:45.661" /><!-- duration: 2ms -->
    <step title="Starting PushDeployAsync" date="2025-12-27T23:07:45.667" /><!-- duration: 2ms -->
    <step title="Writing artifact to /tmp/zipdeploy/8741e094-c9c8-4a26-b18a-c232d2740bf1.zip" date="2025-12-27T23:07:45.686" >
      <step title="Writing multipart request body to /tmp/zipdeploy/8741e094-c9c8-4a26-b18a-c232d2740bf1.zip" date="2025-12-27T23:07:45.688" /><!-- duration: 5ms -->
    </step><!-- duration: 41ms -->
    <step title="Removing previous build artifact&apos;s manifest file" date="2025-12-27T23:07:45.730" >
      <step title="Start deployment in the background" date="2025-12-27T23:07:45.744" >
        <step title="Acquiring Deployment Lock" date="2025-12-27T23:07:45.750" /><!-- duration: 6ms -->
        <step title="Acquired Deployment Lock" date="2025-12-27T23:07:45.778" /><!-- duration: 3ms -->
      </step><!-- duration: 111ms -->
    </step><!-- duration: 133ms -->
    <step title="Outgoing response" date="2025-12-27T23:07:45.866" type="response" statusCode="202" statusText="Accepted" /><!-- duration: 2ms -->
  </step><!-- duration: 216ms -->
